server/__init__.py
server/config.py
server/sample_notebook.ipynb
server/server.py
server/tools/__init__.py
server/tools/definitions.py
singlestore_mcp_server-1.0.0.dist-info/METADATA
singlestore_mcp_server-1.0.0.dist-info/WHEEL
singlestore_mcp_server-1.0.0.dist-info/entry_points.txt
singlestore_mcp_server-1.0.0.dist-info/licenses/LICENSE
singlestore_mcp_server-1.0.0.dist-info/RECORD
