Metadata-Version: 2.4
Name: singlestore_mcp_server
Version: 1.0.0
Summary: SingleStore MCP server
Author-email: Singlestore <support@singlestore.com>
License-File: LICENSE
Requires-Python: >=3.11
Requires-Dist: mcp>=1.3.0
Requires-Dist: singlestoredb>=1.12.0
